{
	"info": {
		"_postman_id": "78d6fdd6-5c54-4830-9a32-1775b1de8caa",
		"name": "api-talks",
		"schema": "https://schema.getpostman.com/json/collection/v2.1.0/collection.json"
	},
	"item": [
		{
			"name": "list",
			"request": {
				"method": "GET",
				"header": [],
				"url": {
					"raw": "http://localhost:3001/api/v1/speakers?highlighted=true",
					"protocol": "http",
					"host": [
						"localhost"
					],
					"port": "3001",
					"path": [
						"api",
						"v1",
						"speakers"
					],
					"query": [
						{
							"key": "highlighted",
							"value": "true"
						}
					]
				}
			},
			"response": []
		},
		{
			"name": "create",
			"request": {
				"method": "POST",
				"header": [],
				"body": {
					"mode": "raw",
					"raw": "{\n    \"title\": \"Bruno Capanema\",\n    \"jobTitle\": \"Tech Lead Hotmart\",\n    \"highlighted\": true,\n    \"avatar\": \"http://localhost:3001/static/images/image-1608493669956.jpg\"\n}",
					"options": {
						"raw": {
							"language": "json"
						}
					}
				},
				"url": {
					"raw": "http://localhost:3001/api/v1/speakers",
					"protocol": "http",
					"host": [
						"localhost"
					],
					"port": "3001",
					"path": [
						"api",
						"v1",
						"speakers"
					]
				}
			},
			"response": []
		},
		{
			"name": "update",
			"request": {
				"method": "PUT",
				"header": [],
				"body": {
					"mode": "raw",
					"raw": "{\n    \"title\": \"Bruno Capanema\",\n    \"jobTitle\": \"Tech Lead Frontend Hotmart\",\n    \"highlighted\": true,\n    \"avatar\": \"http://localhost:3001/static/images/image-1608493669956.jpg\"\n}",
					"options": {
						"raw": {
							"language": "json"
						}
					}
				},
				"url": {
					"raw": "http://localhost:3001/api/v1/speakers/:id",
					"protocol": "http",
					"host": [
						"localhost"
					],
					"port": "3001",
					"path": [
						"api",
						"v1",
						"speakers",
						":id"
					],
					"variable": [
						{
							"key": "id",
							"value": ""
						}
					]
				}
			},
			"response": []
		},
		{
			"name": "destroy",
			"request": {
				"method": "DELETE",
				"header": [],
				"url": {
					"raw": "http://localhost:3001/api/v1/speakers/:id",
					"protocol": "http",
					"host": [
						"localhost"
					],
					"port": "3001",
					"path": [
						"api",
						"v1",
						"speakers",
						":id"
					],
					"variable": [
						{
							"key": "id",
							"value": ""
						}
					]
				}
			},
			"response": []
		},
		{
			"name": "get",
			"request": {
				"method": "GET",
				"header": [],
				"url": {
					"raw": "http://localhost:3001/api/v1/speakers/:id",
					"protocol": "http",
					"host": [
						"localhost"
					],
					"port": "3001",
					"path": [
						"api",
						"v1",
						"speakers",
						":id"
					],
					"variable": [
						{
							"key": "id",
							"value": ""
						}
					]
				}
			},
			"response": []
		},
		{
			"name": "avatarUpload",
			"request": {
				"method": "POST",
				"header": [],
				"body": {
					"mode": "urlencoded",
					"urlencoded": [
						{
							"key": "avatar",
							"value": "",
							"type": "text"
						}
					]
				},
				"url": {
					"raw": "http://localhost:3001/api/v1/speakers/avatar",
					"protocol": "http",
					"host": [
						"localhost"
					],
					"port": "3001",
					"path": [
						"api",
						"v1",
						"speakers",
						"avatar"
					]
				}
			},
			"response": []
		}
	],
	"protocolProfileBehavior": {}
}